doxstractor/__init__.py
doxstractor/nodes.py
doxstractor/utils.py
doxstractor/extractors/__init__.py
doxstractor/extractors/base.py
doxstractor/extractors/category.py
doxstractor/extractors/numeric.py
doxstractor/extractors/text.py
doxstractor/models/__init__.py
doxstractor/models/anthropic.py
doxstractor/models/base.py
doxstractor/models/huggingface_endpoints.py
doxstractor/models/mock.py
doxstractor/models/transformers_classify.py
doxstractor/models/transformers_qa.py
doxstractor-0.1.1.dist-info/LICENSE.md
doxstractor-0.1.1.dist-info/METADATA
doxstractor-0.1.1.dist-info/WHEEL
doxstractor-0.1.1.dist-info/top_level.txt
doxstractor-0.1.1.dist-info/RECORD
